{
    "xbox": {
        "dpad_up": {
            "x": 0.35,
            "y": 0.58
        },
        "dpad_down": {
            "x": 0.35,
            "y": 0.72
        },
        "dpad_left": {
            "x": 0.29,
            "y": 0.65
        },
        "dpad_right": {
            "x": 0.41,
            "y": 0.65
        },
        "a": {
            "x": 0.72,
            "y": 0.65
        },
        "b": {
            "x": 0.8,
            "y": 0.55
        },
        "x": {
            "x": 0.64,
            "y": 0.55
        },
        "y": {
            "x": 0.72,
            "y": 0.45
        },
        "lb": {
            "x": 0.25,
            "y": 0.18
        },
        "rb": {
            "x": 0.75,
            "y": 0.18
        },
        "lt": {
            "x": 0.25,
            "y": 0.02
        },
        "rt": {
            "x": 0.75,
            "y": 0.02
        },
        "l3": {
            "x": 0.28,
            "y": 0.35
        },
        "r3": {
            "x": 0.62,
            "y": 0.75
        },
        "select": {
            "x": 0.43,
            "y": 0.35
        },
        "start": {
            "x": 0.57,
            "y": 0.35
        },
        "home": {
            "x": 0.5,
            "y": 0.45
        }
    },
    "playstation": {
        "dpad_up": {
            "x": 0.28,
            "y": 0.28
        },
        "dpad_down": {
            "x": 0.28,
            "y": 0.42
        },
        "dpad_left": {
            "x": 0.22,
            "y": 0.35
        },
        "dpad_right": {
            "x": 0.34,
            "y": 0.35
        },
        "a": {
            "x": 0.72,
            "y": 0.65
        },
        "b": {
            "x": 0.8,
            "y": 0.55
        },
        "x": {
            "x": 0.64,
            "y": 0.55
        },
        "y": {
            "x": 0.72,
            "y": 0.45
        },
        "lb": {
            "x": 0.25,
            "y": 0.18
        },
        "rb": {
            "x": 0.75,
            "y": 0.18
        },
        "lt": {
            "x": 0.25,
            "y": 0.02
        },
        "rt": {
            "x": 0.75,
            "y": 0.02
        },
        "l3": {
            "x": 0.35,
            "y": 0.65
        },
        "r3": {
            "x": 0.62,
            "y": 0.75
        },
        "select": {
            "x": 0.43,
            "y": 0.35
        },
        "start": {
            "x": 0.57,
            "y": 0.35
        },
        "home": {
            "x": 0.5,
            "y": 0.45
        }
    }
}